crawlee/__init__.py
crawlee/_browserforge_workaround.py
crawlee/_cli.py
crawlee/_consts.py
crawlee/_log_config.py
crawlee/_request.py
crawlee/_service_locator.py
crawlee/_types.py
crawlee/configuration.py
crawlee/errors.py
crawlee/proxy_configuration.py
crawlee/py.typed
crawlee/router.py
crawlee/_autoscaling/__init__.py
crawlee/_autoscaling/_types.py
crawlee/_autoscaling/autoscaled_pool.py
crawlee/_autoscaling/py.typed
crawlee/_autoscaling/snapshotter.py
crawlee/_autoscaling/system_status.py
crawlee/_utils/__init__.py
crawlee/_utils/blocked.py
crawlee/_utils/byte_size.py
crawlee/_utils/console.py
crawlee/_utils/context.py
crawlee/_utils/crypto.py
crawlee/_utils/docs.py
crawlee/_utils/file.py
crawlee/_utils/globs.py
crawlee/_utils/html_to_text.py
crawlee/_utils/models.py
crawlee/_utils/raise_if_too_many_kwargs.py
crawlee/_utils/recoverable_state.py
crawlee/_utils/recurring_task.py
crawlee/_utils/requests.py
crawlee/_utils/robots.py
crawlee/_utils/sitemap.py
crawlee/_utils/system.py
crawlee/_utils/time.py
crawlee/_utils/try_import.py
crawlee/_utils/urls.py
crawlee/_utils/wait.py
crawlee/_utils/web.py
crawlee/browsers/__init__.py
crawlee/browsers/_browser_controller.py
crawlee/browsers/_browser_plugin.py
crawlee/browsers/_browser_pool.py
crawlee/browsers/_playwright_browser.py
crawlee/browsers/_playwright_browser_controller.py
crawlee/browsers/_playwright_browser_plugin.py
crawlee/browsers/_types.py
crawlee/browsers/py.typed
crawlee/crawlers/__init__.py
crawlee/crawlers/_types.py
crawlee/crawlers/py.typed
crawlee/crawlers/_abstract_http/__init__.py
crawlee/crawlers/_abstract_http/_abstract_http_crawler.py
crawlee/crawlers/_abstract_http/_abstract_http_parser.py
crawlee/crawlers/_abstract_http/_http_crawling_context.py
crawlee/crawlers/_abstract_http/py.typed
crawlee/crawlers/_adaptive_playwright/__init__.py
crawlee/crawlers/_adaptive_playwright/_adaptive_playwright_crawler.py
crawlee/crawlers/_adaptive_playwright/_adaptive_playwright_crawler_statistics.py
crawlee-1.3.1.dist-info/METADATA
crawlee-1.3.1.dist-info/WHEEL
crawlee-1.3.1.dist-info/entry_points.txt
crawlee-1.3.1.dist-info/licenses/LICENSE
crawlee-1.3.1.dist-info/RECORD
