Metadata-Version: 2.4
Name: crawlee
Version: 1.3.1
Summary: Crawlee for Python
Project-URL: Apify Homepage, https://apify.com
Project-URL: Changelog, https://crawlee.dev/python/docs/changelog
Project-URL: Discord, https://discord.com/invite/jyEM2PRvMU
Project-URL: Documentation, https://crawlee.dev/python/docs/quick-start
Project-URL: Homepage, https://crawlee.dev/python
Project-URL: Issue Tracker, https://github.com/apify/crawlee-python/issues
Project-URL: Release Notes, https://crawlee.dev/python/docs/upgrading
Project-URL: Source Code, https://github.com/apify/crawlee-python
Author-email: "Apify Technologies s.r.o." <support@apify.com>
License:                                  Apache License
License-File: LICENSE
Keywords: apify,automation,chrome,crawlee,crawler,headless,scraper,scraping
Classifier: Development Status :: 5 - Production/Stable
Classifier: Environment :: Console
Classifier: Intended Audience :: Developers
Classifier: License :: OSI Approved :: Apache Software License
Classifier: Operating System :: OS Independent
Classifier: Programming Language :: Python :: 3.10
Classifier: Programming Language :: Python :: 3.11
Classifier: Programming Language :: Python :: 3.12
Classifier: Programming Language :: Python :: 3.13
Classifier: Programming Language :: Python :: 3.14
Classifier: Topic :: Software Development :: Libraries
Requires-Python: >=3.10
Requires-Dist: async-timeout>=5.0.1
Requires-Dist: cachetools>=5.5.0
Requires-Dist: colorama>=0.4.0
Requires-Dist: impit>=0.8.0
Requires-Dist: more-itertools>=10.2.0
Requires-Dist: protego>=0.5.0
Requires-Dist: psutil>=6.0.0
Requires-Dist: pydantic-settings>=2.12.0
Requires-Dist: pydantic>=2.11.0
Requires-Dist: pyee>=9.0.0
Requires-Dist: tldextract>=5.1.0
Requires-Dist: typing-extensions>=4.1.0
Requires-Dist: yarl>=1.18.0
Provides-Extra: adaptive-crawler
Requires-Dist: apify-fingerprint-datapoints>=0.0.2; extra == 'adaptive-crawler'
Requires-Dist: browserforge>=1.2.3; extra == 'adaptive-crawler'
Requires-Dist: jaro-winkler>=2.0.3; extra == 'adaptive-crawler'
Requires-Dist: playwright>=1.27.0; extra == 'adaptive-crawler'
Requires-Dist: scikit-learn>=1.6.0; extra == 'adaptive-crawler'
Provides-Extra: all
Requires-Dist: aiosqlite>=0.21.0; extra == 'all'
Requires-Dist: apify-fingerprint-datapoints>=0.0.2; extra == 'all'
Requires-Dist: asyncpg>=0.24.0; extra == 'all'
Requires-Dist: beautifulsoup4[lxml]>=4.12.0; extra == 'all'
Requires-Dist: browserforge>=1.2.3; extra == 'all'
Requires-Dist: cookiecutter>=2.6.0; extra == 'all'
Requires-Dist: curl-cffi>=0.9.0; extra == 'all'
Requires-Dist: html5lib>=1.0; extra == 'all'
Requires-Dist: httpx[brotli,http2,zstd]>=0.27.0; extra == 'all'
Requires-Dist: inquirer>=3.3.0; extra == 'all'
Requires-Dist: jaro-winkler>=2.0.3; extra == 'all'
Requires-Dist: opentelemetry-api>=1.34.1; extra == 'all'
Requires-Dist: opentelemetry-distro[otlp]>=0.54; extra == 'all'
Requires-Dist: opentelemetry-instrumentation-httpx>=0.54; extra == 'all'
Requires-Dist: opentelemetry-instrumentation>=0.54; extra == 'all'
Requires-Dist: opentelemetry-sdk>=1.34.1; extra == 'all'
Requires-Dist: opentelemetry-semantic-conventions>=0.54; extra == 'all'
Requires-Dist: parsel>=1.10.0; extra == 'all'
Requires-Dist: playwright>=1.27.0; extra == 'all'
Requires-Dist: redis[hiredis]>=7.0.0; extra == 'all'
Requires-Dist: rich>=13.9.0; extra == 'all'
Requires-Dist: scikit-learn>=1.6.0; extra == 'all'
Requires-Dist: sqlalchemy[asyncio]<3.0.0,>=2.0.0; extra == 'all'
Requires-Dist: typer>=0.12.0; extra == 'all'
Requires-Dist: wrapt>=1.17.0; extra == 'all'
Provides-Extra: beautifulsoup
Requires-Dist: beautifulsoup4[lxml]>=4.12.0; extra == 'beautifulsoup'
Requires-Dist: html5lib>=1.0; extra == 'beautifulsoup'
Provides-Extra: cli
Requires-Dist: cookiecutter>=2.6.0; extra == 'cli'
Requires-Dist: inquirer>=3.3.0; extra == 'cli'
Requires-Dist: rich>=13.9.0; extra == 'cli'
Requires-Dist: typer>=0.12.0; extra == 'cli'
Provides-Extra: curl-impersonate
Requires-Dist: curl-cffi>=0.9.0; extra == 'curl-impersonate'
Provides-Extra: httpx
Requires-Dist: apify-fingerprint-datapoints>=0.0.2; extra == 'httpx'
Requires-Dist: browserforge>=1.2.3; extra == 'httpx'
Requires-Dist: httpx[brotli,http2,zstd]>=0.27.0; extra == 'httpx'
Provides-Extra: otel
Requires-Dist: opentelemetry-api>=1.34.1; extra == 'otel'
Requires-Dist: opentelemetry-distro[otlp]>=0.54; extra == 'otel'
Requires-Dist: opentelemetry-instrumentation-httpx>=0.54; extra == 'otel'
Requires-Dist: opentelemetry-instrumentation>=0.54; extra == 'otel'
Requires-Dist: opentelemetry-sdk>=1.34.1; extra == 'otel'
Requires-Dist: opentelemetry-semantic-conventions>=0.54; extra == 'otel'
Requires-Dist: wrapt>=1.17.0; extra == 'otel'
Provides-Extra: parsel
Requires-Dist: parsel>=1.10.0; extra == 'parsel'
Provides-Extra: playwright
Requires-Dist: apify-fingerprint-datapoints>=0.0.2; extra == 'playwright'
Requires-Dist: browserforge>=1.2.3; extra == 'playwright'
Requires-Dist: playwright>=1.27.0; extra == 'playwright'
Provides-Extra: redis
Requires-Dist: redis[hiredis]>=7.0.0; extra == 'redis'
Provides-Extra: sql-postgres
Requires-Dist: asyncpg>=0.24.0; extra == 'sql-postgres'
Requires-Dist: sqlalchemy[asyncio]<3.0.0,>=2.0.0; extra == 'sql-postgres'
Provides-Extra: sql-sqlite
Requires-Dist: aiosqlite>=0.21.0; extra == 'sql-sqlite'
Requires-Dist: sqlalchemy[asyncio]<3.0.0,>=2.0.0; extra == 'sql-sqlite'
